[
  {
    "Code Name": "B070220XX_11028.jpg",
    "Name": "bossam",
    "W": "0.509053497942387",
    "H": "0.66358024691358",
    "File Format": "jpg",
    "Cat 1": "07",
    "Cat 2": "02",
    "Cat 3": "20",
    "Cat 4": "xx",
    "Annotation Type": "binding",
    "Point(x,y)": "0.620781893004115,0.610185185185185",
    "Label": "0",
    "Serving Size": "xx",
    "Camera Angle": "xx",
    "Cardinal Angle": "xx",
    "Color of Container": "xx",
    "Material of Container": "xx",
    "Illuminance": "xx"
  }
]