[
  {
    "Code Name": "A020115XX_11591.jpg",
    "Name": "bolippang",
    "W": "0.488477366255144",
    "H": "0.798765432098765",
    "File Format": "jpg",
    "Cat 1": "02",
    "Cat 2": "01",
    "Cat 3": "15",
    "Cat 4": "xx",
    "Annotation Type": "binding",
    "Point(x,y)": "0.675514403292181,0.4",
    "Label": "0",
    "Serving Size": "xx",
    "Camera Angle": "xx",
    "Cardinal Angle": "xx",
    "Color of Container": "xx",
    "Material of Container": "xx",
    "Illuminance": "xx"
  },
  {
    "Code Name": "A020115XX_11591.jpg",
    "Name": "bolippang",
    "W": "0.398353909465021",
    "H": "0.383950617283951",
    "File Format": "jpg",
    "Cat 1": "02",
    "Cat 2": "01",
    "Cat 3": "15",
    "Cat 4": "xx",
    "Annotation Type": "binding",
    "Point(x,y)": "0.262139917695473,0.691975308641975",
    "Label": "0",
    "Serving Size": "xx",
    "Camera Angle": "xx",
    "Cardinal Angle": "xx",
    "Color of Container": "xx",
    "Material of Container": "xx",
    "Illuminance": "xx"
  }
]