[
  {
    "Code Name": "A020115XX_13050.jpg",
    "Name": "bolippang",
    "W": "0.532510288065844",
    "H": "0.672510958046337",
    "File Format": "jpg",
    "Cat 1": "02",
    "Cat 2": "01",
    "Cat 3": "15",
    "Cat 4": "xx",
    "Annotation Type": "binding",
    "Point(x,y)": "0.723045267489712,0.45648090169067",
    "Label": "0",
    "Serving Size": "xx",
    "Camera Angle": "xx",
    "Cardinal Angle": "xx",
    "Color of Container": "xx",
    "Material of Container": "xx",
    "Illuminance": "xx"
  },
  {
    "Code Name": "A020115XX_13050.jpg",
    "Name": "bolippang",
    "W": "0.430041152263374",
    "H": "0.708829054477145",
    "File Format": "jpg",
    "Cat 1": "02",
    "Cat 2": "01",
    "Cat 3": "15",
    "Cat 4": "xx",
    "Annotation Type": "binding",
    "Point(x,y)": "0.26440329218107,0.473387601753287",
    "Label": "0",
    "Serving Size": "xx",
    "Camera Angle": "xx",
    "Cardinal Angle": "xx",
    "Color of Container": "xx",
    "Material of Container": "xx",
    "Illuminance": "xx"
  }
]