[
  {
    "Code Name": "A020115XX_03983.jpg",
    "Name": "bolippang",
    "W": "0.247452",
    "H": "0.400446",
    "File Format": "jpg",
    "Cat 1": "02",
    "Cat 2": "01",
    "Cat 3": "15",
    "Cat 4": "xx",
    "Annotation Type": "binding",
    "Point(x,y)": "0.876274,0.799777",
    "Label": "0",
    "Serving Size": "xx",
    "Camera Angle": "xx",
    "Cardinal Angle": "xx",
    "Color of Container": "xx",
    "Material of Container": "xx",
    "Illuminance": "xx"
  },
  {
    "Code Name": "A020115XX_03983.jpg",
    "Name": "bolippang",
    "W": "0.913519",
    "H": "0.796910",
    "File Format": "jpg",
    "Cat 1": "02",
    "Cat 2": "01",
    "Cat 3": "15",
    "Cat 4": "xx",
    "Annotation Type": "binding",
    "Point(x,y)": "0.543241,0.398455",
    "Label": "0",
    "Serving Size": "xx",
    "Camera Angle": "xx",
    "Cardinal Angle": "xx",
    "Color of Container": "xx",
    "Material of Container": "xx",
    "Illuminance": "xx"
  },
  {
    "Code Name": "A020115XX_03983.jpg",
    "Name": "bolippang",
    "W": "0.391381",
    "H": "0.292303",
    "File Format": "jpg",
    "Cat 1": "02",
    "Cat 2": "01",
    "Cat 3": "15",
    "Cat 4": "xx",
    "Annotation Type": "binding",
    "Point(x,y)": "0.583787,0.853848",
    "Label": "0",
    "Serving Size": "xx",
    "Camera Angle": "xx",
    "Cardinal Angle": "xx",
    "Color of Container": "xx",
    "Material of Container": "xx",
    "Illuminance": "xx"
  }
]