[
  {
    "Code Name": "A020115XX_14155.jpg",
    "Name": "bolippang",
    "W": "0.724611161939616",
    "H": "0.95264241592313",
    "File Format": "jpg",
    "Cat 1": "02",
    "Cat 2": "01",
    "Cat 3": "15",
    "Cat 4": "xx",
    "Annotation Type": "binding",
    "Point(x,y)": "0.529734675205855,0.523678792038435",
    "Label": "0",
    "Serving Size": "xx",
    "Camera Angle": "xx",
    "Cardinal Angle": "xx",
    "Color of Container": "xx",
    "Material of Container": "xx",
    "Illuminance": "xx"
  }
]