[
  {
    "Code Name": "A020115XX_13912.jpg",
    "Name": "bolippang",
    "W": "0.356172839506173",
    "H": "0.237860082304527",
    "File Format": "jpg",
    "Cat 1": "02",
    "Cat 2": "01",
    "Cat 3": "15",
    "Cat 4": "xx",
    "Annotation Type": "binding",
    "Point(x,y)": "0.697222222222222,0.849382716049383",
    "Label": "0",
    "Serving Size": "xx",
    "Camera Angle": "xx",
    "Cardinal Angle": "xx",
    "Color of Container": "xx",
    "Material of Container": "xx",
    "Illuminance": "xx"
  },
  {
    "Code Name": "A020115XX_13912.jpg",
    "Name": "bolippang",
    "W": "0.262962962962963",
    "H": "0.176954732510288",
    "File Format": "jpg",
    "Cat 1": "02",
    "Cat 2": "01",
    "Cat 3": "15",
    "Cat 4": "xx",
    "Annotation Type": "binding",
    "Point(x,y)": "0.408641975308642,0.48641975308642",
    "Label": "0",
    "Serving Size": "xx",
    "Camera Angle": "xx",
    "Cardinal Angle": "xx",
    "Color of Container": "xx",
    "Material of Container": "xx",
    "Illuminance": "xx"
  }
]